funsecret/__init__.py
funsecret/base.py
funsecret/fernet.py
funsecret/secret.py
funsecret/sqlalchemy/__init__.py
funsecret/sqlalchemy/base.py
funsecret/sqlalchemy/engine.py
funsecret-202308241745.dist-info/METADATA
funsecret-202308241745.dist-info/WHEEL
funsecret-202308241745.dist-info/top_level.txt
funsecret-202308241745.dist-info/RECORD
