Metadata-Version: 2.1
Name: funsecret
Version: 202308241745
Summary: funsecret
Home-page: https://github.com/farfarfun/funsecret
Author: bingtao
Author-email: 1007530194@qq.com
Requires-Dist: funbuild
Requires-Dist: sqlalchemy
Requires-Dist: pandas
